{
  "id": "5134205",
  "name": "流浪猫",
  "font_family": "iconfont",
  "css_prefix_text": "icon-",
  "description": "",
  "glyphs": [
    {
      "icon_id": "1253",
      "name": "收藏",
      "font_class": "shoucang",
      "unicode": "e600",
      "unicode_decimal": 58880
    },
    {
      "icon_id": "577313",
      "name": "加号1",
      "font_class": "jiahao1",
      "unicode": "e727",
      "unicode_decimal": 59175
    },
    {
      "icon_id": "658044",
      "name": "解锁",
      "font_class": "jiesuo",
      "unicode": "e669",
      "unicode_decimal": 58985
    },
    {
      "icon_id": "1075267",
      "name": "cat",
      "font_class": "cat",
      "unicode": "e65e",
      "unicode_decimal": 58974
    },
    {
      "icon_id": "1304896",
      "name": "用户",
      "font_class": "yonghu",
      "unicode": "e624",
      "unicode_decimal": 58916
    },
    {
      "icon_id": "2674878",
      "name": "箭头 上",
      "font_class": "jiantoushang",
      "unicode": "e62c",
      "unicode_decimal": 58924
    },
    {
      "icon_id": "4354835",
      "name": "闭眼睛",
      "font_class": "biyanjing",
      "unicode": "e901",
      "unicode_decimal": 59649
    },
    {
      "icon_id": "5026283",
      "name": "加",
      "font_class": "jjia-",
      "unicode": "e6a9",
      "unicode_decimal": 59049
    },
    {
      "icon_id": "6775644",
      "name": "爱心",
      "font_class": "aixin",
      "unicode": "eca1",
      "unicode_decimal": 60577
    },
    {
      "icon_id": "10079558",
      "name": "右箭头",
      "font_class": "youjiantou",
      "unicode": "e62d",
      "unicode_decimal": 58925
    },
    {
      "icon_id": "11372728",
      "name": "眼睛",
      "font_class": "yanjing",
      "unicode": "e8bf",
      "unicode_decimal": 59583
    },
    {
      "icon_id": "16921559",
      "name": "搜索",
      "font_class": "sousuo",
      "unicode": "e7ec",
      "unicode_decimal": 59372
    },
    {
      "icon_id": "25150306",
      "name": "男女-男",
      "font_class": "nannv-nan",
      "unicode": "e601",
      "unicode_decimal": 58881
    },
    {
      "icon_id": "25150378",
      "name": "男女-女",
      "font_class": "nannv-nv",
      "unicode": "e602",
      "unicode_decimal": 58882
    },
    {
      "icon_id": "25839046",
      "name": "下、箭头下",
      "font_class": "a-xiajiantouxia",
      "unicode": "e60e",
      "unicode_decimal": 58894
    },
    {
      "icon_id": "29657596",
      "name": "叉",
      "font_class": "cha",
      "unicode": "e68b",
      "unicode_decimal": 59019
    },
    {
      "icon_id": "41587091",
      "name": "箭头-左",
      "font_class": "jiantou-zuo",
      "unicode": "e630",
      "unicode_decimal": 58928
    },
    {
      "icon_id": "42905921",
      "name": "布偶猫",
      "font_class": "buoumao",
      "unicode": "e647",
      "unicode_decimal": 58951
    },
    {
      "icon_id": "42905929",
      "name": "橘猫",
      "font_class": "jumao",
      "unicode": "e648",
      "unicode_decimal": 58952
    },
    {
      "icon_id": "42905930",
      "name": "更多猫宠",
      "font_class": "gengduomaochong",
      "unicode": "e649",
      "unicode_decimal": 58953
    },
    {
      "icon_id": "42905931",
      "name": "蓝猫",
      "font_class": "lanmao",
      "unicode": "e64a",
      "unicode_decimal": 58954
    },
    {
      "icon_id": "42905932",
      "name": "奶牛猫",
      "font_class": "nainiumao",
      "unicode": "e64b",
      "unicode_decimal": 58955
    },
    {
      "icon_id": "43415539",
      "name": "白猫",
      "font_class": "baimao",
      "unicode": "e64c",
      "unicode_decimal": 58956
    },
    {
      "icon_id": "43415566",
      "name": "三花猫",
      "font_class": "sanhuamao",
      "unicode": "e64d",
      "unicode_decimal": 58957
    },
    {
      "icon_id": "43415613",
      "name": "黑猫",
      "font_class": "heimao",
      "unicode": "e64e",
      "unicode_decimal": 58958
    },
    {
      "icon_id": "43415640",
      "name": "暹罗猫",
      "font_class": "xianluomao",
      "unicode": "e64f",
      "unicode_decimal": 58959
    }
  ]
}
